<?xml version="1.0" encoding="UTF-8"?>
<preferences>
 <debug showDebugMenu="0" />
 <systemtable filter="All Interfaces" showResetDomains="0" showClockDomains="0">
  <columns>
   <connections preferredWidth="223" />
   <irq preferredWidth="34" />
  </columns>
 </systemtable>
 <library
   expandedCategories="Library/Processors and Peripherals,Library/Interface Protocols/Serial,Library/Interface Protocols,Library,Project" />
 <window width="976" height="1038" x="952" y="0" />
 <generation synthesis="VHDL" block_symbol_file="0" />
</preferences>
